vimage/__init__.py
vimage/apps.py
vimage/core/__init__.py
vimage/core/base.py
vimage/core/checker.py
vimage/core/const.py
vimage/core/exceptions.py
vimage/core/validator_types.py
vimage/locale/el/LC_MESSAGES/django.mo
vimage/locale/el/LC_MESSAGES/django.po
django_vimage-1.2.0.dist-info/AUTHORS.rst
django_vimage-1.2.0.dist-info/LICENSE
django_vimage-1.2.0.dist-info/METADATA
django_vimage-1.2.0.dist-info/WHEEL
django_vimage-1.2.0.dist-info/top_level.txt
django_vimage-1.2.0.dist-info/RECORD
