Metadata-Version: 2.1
Name: django-vimage
Version: 1.2.0
Summary: Image validation (for the Django Admin) as a breeze. 
Home-page: https://github.com/manikos/django-vimage
Author: Nick Mavrakis
Author-email: mavrakis.n@gmail.com
License: MIT
Keywords: django image-validation django-admin easy-to-use
Platform: UNKNOWN
Classifier: Development Status :: 5 - Production/Stable
Classifier: Environment :: Web Environment
Classifier: Framework :: Django
Classifier: Framework :: Django :: 2.0
Classifier: Framework :: Django :: 3.0
Classifier: Framework :: Django :: 4.0
Classifier: Intended Audience :: Developers
Classifier: License :: OSI Approved :: MIT License
Classifier: Operating System :: OS Independent
Classifier: Natural Language :: English
Classifier: Programming Language :: Python :: 3
Classifier: Programming Language :: Python :: 3.6
Classifier: Topic :: Internet :: WWW/HTTP
Classifier: Topic :: Internet :: WWW/HTTP :: Dynamic Content
Requires-Python: >=3.6
License-File: LICENSE
License-File: AUTHORS.rst
Requires-Dist: Django (>=2)
Requires-Dist: Pillow (>=4.0.0)
